resumable/__init__.py
resumable_urlretrieve-0.1.6.dist-info/METADATA
resumable_urlretrieve-0.1.6.dist-info/WHEEL
resumable_urlretrieve-0.1.6.dist-info/top_level.txt
resumable_urlretrieve-0.1.6.dist-info/RECORD
